notesctl/__init__.py
notesctl/cli.py
notesctl/exporter.py
notesctl/converter/__init__.py
notesctl/converter/markdown.py
notesctl/database/__init__.py
notesctl/database/connection.py
notesctl/database/models.py
notesctl/database/queries.py
notesctl/parser/__init__.py
notesctl/parser/note_parser.py
notesctl/parser/protobuf/__init__.py
notesctl/parser/protobuf/notestore_pb2.py
notesctl-1.0.2.dist-info/METADATA
notesctl-1.0.2.dist-info/WHEEL
notesctl-1.0.2.dist-info/entry_points.txt
notesctl-1.0.2.dist-info/licenses/LICENSE
notesctl-1.0.2.dist-info/RECORD
