Metadata-Version: 2.4
Name: notesctl
Version: 1.0.2
Summary: Export Apple iCloud Notes to Markdown files safely
Project-URL: Homepage, https://github.com/jwmoss/notesctl
Project-URL: Repository, https://github.com/jwmoss/notesctl
Project-URL: Documentation, https://github.com/jwmoss/notesctl#readme
Project-URL: Issues, https://github.com/jwmoss/notesctl/issues
Project-URL: Changelog, https://github.com/jwmoss/notesctl/blob/main/CHANGELOG.md
License-Expression: MIT
License-File: LICENSE
Keywords: apple,export,icloud,markdown,notes
Classifier: Development Status :: 4 - Beta
Classifier: Environment :: Console
Classifier: Intended Audience :: End Users/Desktop
Classifier: License :: OSI Approved :: MIT License
Classifier: Operating System :: MacOS
Classifier: Programming Language :: Python :: 3
Classifier: Programming Language :: Python :: 3.11
Classifier: Programming Language :: Python :: 3.12
Classifier: Programming Language :: Python :: 3.13
Classifier: Topic :: Utilities
Classifier: Typing :: Typed
Requires-Python: >=3.11
Requires-Dist: pillow>=10.0.0
Requires-Dist: protobuf>=4.25.0
Requires-Dist: rich>=13.0.0
Requires-Dist: typer>=0.9.0
Provides-Extra: dev
Requires-Dist: grpcio-tools>=1.60.0; extra == 'dev'
Requires-Dist: pytest-cov>=4.0.0; extra == 'dev'
Requires-Dist: pytest>=7.0.0; extra == 'dev'
Requires-Dist: ruff>=0.8.0; extra == 'dev'
Requires-Dist: ty>=0.0.1; extra == 'dev'
